streamlit_keycloak_lex/__init__.py
streamlit_keycloak_lex/frontend/public/bootstrap.min.css
streamlit_keycloak_lex/frontend/public/check-sso.html
streamlit_keycloak_lex/frontend/public/index.html
streamlit_keycloak_lex/frontend/public/login.html
streamlit_keycloak_lex/frontend/public/build/bundle.css
streamlit_keycloak_lex/frontend/public/build/bundle.css.map
streamlit_keycloak_lex/frontend/public/build/bundle.js
streamlit_keycloak_lex/frontend/public/build/bundle.js.map
streamlit_keycloak_lex-1.0.5.dist-info/licenses/LICENSE
streamlit_keycloak_lex-1.0.5.dist-info/METADATA
streamlit_keycloak_lex-1.0.5.dist-info/WHEEL
streamlit_keycloak_lex-1.0.5.dist-info/top_level.txt
streamlit_keycloak_lex-1.0.5.dist-info/RECORD
