Metadata-Version: 2.4
Name: streamlit-keycloak-lex
Version: 1.0.5
Summary: Keycloak authentication for Streamlit
Home-page: https://github.com/LundIT/streamlit-keycloak-lex
Author: Melih Sünbül
Author-email: m.sunbul@lund-it.com
Requires-Python: >=3.7
License-File: LICENSE
Requires-Dist: streamlit-local-storage
Requires-Dist: streamlit>=0.63
Dynamic: author
Dynamic: author-email
Dynamic: description
Dynamic: description-content-type
Dynamic: home-page
Dynamic: license-file
Dynamic: requires-dist
Dynamic: requires-python
Dynamic: summary
